nprintml/__init__.py
nprintml/__main__.py
nprintml/cli.py
nprintml/pipeline.py
nprintml/label/__init__.py
nprintml/label/step.py
nprintml/label/aggregator/__init__.py
nprintml/label/aggregator/base.py
nprintml/label/aggregator/index.py
nprintml/label/aggregator/pcap.py
nprintml/learn/__init__.py
nprintml/learn/automl.py
nprintml/learn/step.py
nprintml/net/__init__.py
nprintml/net/execute.py
nprintml/net/install.py
nprintml/net/step.py
nprintml/util/__init__.py
nprintml/util/fileformat.py
nprintml/util/interface.py
nprintml/util/io.py
nprintml/util/iteration.py
nprintml-1.1.2.dist-info/LICENSE
nprintml-1.1.2.dist-info/METADATA
nprintml-1.1.2.dist-info/WHEEL
nprintml-1.1.2.dist-info/entry_points.txt
nprintml-1.1.2.dist-info/top_level.txt
nprintml-1.1.2.dist-info/RECORD
