Metadata-Version: 2.1
Name: nprintml
Version: 1.1.2
Summary: Fully automated traffic analysis with nPrint
Home-page: https://github.com/nprint/nprintml
License: License :: OSI Approved :: Apache Software License
Platform: UNKNOWN
Classifier: Development Status :: 4 - Beta
Classifier: Intended Audience :: Developers
Classifier: Intended Audience :: Education
Classifier: Intended Audience :: Information Technology
Classifier: Intended Audience :: Science/Research
Classifier: Intended Audience :: System Administrators
Classifier: Intended Audience :: Telecommunications Industry
Classifier: Programming Language :: Python :: 3
Classifier: Programming Language :: Python :: 3.6
Classifier: Programming Language :: Python :: 3.7
Classifier: Programming Language :: Python :: 3.8
Classifier: Topic :: Internet
Classifier: Topic :: Software Development :: Libraries
Classifier: Topic :: Software Development :: Libraries :: Python Modules
Classifier: Topic :: Scientific/Engineering
Classifier: Topic :: Scientific/Engineering :: Artificial Intelligence
Classifier: Topic :: System :: Networking :: Monitoring
Classifier: Topic :: Security
Classifier: Topic :: Terminals
Requires-Python: >=3.6,<3.9
Requires-Dist: argparse-formatter (~=1.4)
Requires-Dist: Dickens (~=1.0.1)
Requires-Dist: autogluon.tabular (~=0.1.0)
Requires-Dist: numpy (==1.19.5)
Requires-Dist: pandas (~=1.1.5)
Requires-Dist: pyarrow (~=4.0.0)
Requires-Dist: matplotlib (~=3.3.4)
Requires-Dist: seaborn (~=0.11.1)
Requires-Dist: toml (~=0.10.2)
Provides-Extra: dev
Requires-Dist: argcmdr (==0.7.0) ; extra == 'dev'
Requires-Dist: argparse-formatter (~=1.4) ; extra == 'dev'
Requires-Dist: bumpversion (==0.6.0) ; extra == 'dev'
Requires-Dist: twine (==3.4.0) ; extra == 'dev'
Requires-Dist: wheel (==0.36.2) ; extra == 'dev'
Requires-Dist: tox (==3.23.0) ; extra == 'dev'
Provides-Extra: test
Requires-Dist: tox (==3.23.0) ; extra == 'test'
